pyrlottie/__init__.py
pyrlottie/build_steps_gif2webp.md
pyrlottie/build_steps_rlottie.md
pyrlottie/linux_aarch64/gif2webp
pyrlottie/linux_aarch64/lottie2gif
pyrlottie/linux_x86_64/gif2webp
pyrlottie/linux_x86_64/lottie2gif
pyrlottie/windows_amd64/gif2webp.exe
pyrlottie/windows_amd64/lottie2gif.exe
pyrlottie-2024.dist-info/LICENSE.md
pyrlottie-2024.dist-info/METADATA
pyrlottie-2024.dist-info/WHEEL
pyrlottie-2024.dist-info/RECORD
